{
    "data": [
      {
        "carePakType": "CarePAK Plus",
        "carePakSku": 3614373586,
        "carePakSkuName": "CPPBINO_9836",
        "company": "ISOSPHERE",
        "productGroup": "Medical",
        "productCode": "MD",
        "level2Code": "C5",
        "dataRecovery": "Y",
        "prefix": "MSPDA",
        "term": 2,
        "edit": "<a href=\"#\" onclick=\"showEditSkuModal(3614373586)\">EDIT</a>"
      },
      {
        "carePakType": "CarePAK Plus",
        "carePakSku": 9789900977,
        "carePakSkuName": "CRRLINO_0504",
        "company": "HARMONEY",
        "productGroup": "Boniculars",
        "productCode": "MD",
        "level2Code": "B3",
        "dataRecovery": "Y",
        "prefix": "MSPDA",
        "term": 13,
        "edit": "<a href=\"#\" onclick=\"showEditSkuModal(9789900977)\">EDIT</a>"
      },
      {
        "carePakType": "CarePAK Plus",
        "carePakSku": 4171768644,
        "carePakSkuName": "CPPBINO_2894",
        "company": "CENTREGY",
        "productGroup": "Film",
        "productCode": "AL",
        "level2Code": "B3",
        "dataRecovery": "Y",
        "prefix": "OTHER",
        "term": 11,
        "edit": "<a href=\"#\" onclick=\"showEditSkuModal(4171768644)\">EDIT</a>"
      },
      {
        "carePakType": "CarePAK Plus",
        "carePakSku": 3154195908,
        "carePakSkuName": "CPPBINO_9836",
        "company": "ZILLAN",
        "productGroup": "Camera",
        "productCode": "BN",
        "level2Code": "A2",
        "dataRecovery": "N",
        "prefix": "ESPDAR",
        "term": 11,
        "edit": "<a href=\"#\" onclick=\"showEditSkuModal(3154195908)\">EDIT</a>"
      },
      {
        "carePakType": "CarePAK Plus",
        "carePakSku": 9265445373,
        "carePakSkuName": "CPPBINO_2894",
        "company": "DUOFLEX",
        "productGroup": "Boniculars",
        "productCode": "AL",
        "level2Code": "A2",
        "dataRecovery": "N",
        "prefix": "ESPDAR",
        "term": 16,
        "edit": "<a href=\"#\" onclick=\"showEditSkuModal(9265445373)\">EDIT</a>"
      },
      {
        "carePakType": "CarePAK Plus",
        "carePakSku": 6333016646,
        "carePakSkuName": "CPPBINO_29845",
        "company": "PLASTO",
        "productGroup": "Camera",
        "productCode": "TS",
        "level2Code": "A2",
        "dataRecovery": "Y",
        "prefix": "MSPDA",
        "term": 11,
        "edit": "<a href=\"#\" onclick=\"showEditSkuModal(6333016646)\">EDIT</a>"
      },
      {
        "carePakType": "CarePAK Plus",
        "carePakSku": 9046983973,
        "carePakSkuName": "CRRLINO_0504",
        "company": "BULLZONE",
        "productGroup": "Camera",
        "productCode": "AL",
        "level2Code": "A9",
        "dataRecovery": "N",
        "prefix": "ESPDA",
        "term": 2,
        "edit": "<a href=\"#\" onclick=\"showEditSkuModal(9046983973)\">EDIT</a>"
      },
      {
        "carePakType": "CarePAK Plus",
        "carePakSku": 8318897884,
        "carePakSkuName": "CPPBINO_0504",
        "company": "JAMNATION",
        "productGroup": "Camera",
        "productCode": "CM",
        "level2Code": "C5",
        "dataRecovery": "N",
        "prefix": "ESPDAR",
        "term": 1,
        "edit": "<a href=\"#\" onclick=\"showEditSkuModal(8318897884)\">EDIT</a>"
      },
      {
        "carePakType": "CarePAK Plus",
        "carePakSku": 8915440796,
        "carePakSkuName": "CRRLINO_0504",
        "company": "COASH",
        "productGroup": "Film",
        "productCode": "BN",
        "level2Code": "A9",
        "dataRecovery": "Y",
        "prefix": "MSPDAR",
        "term": 19,
        "edit": "<a href=\"#\" onclick=\"showEditSkuModal(8915440796)\">EDIT</a>"
      },
      {
        "carePakType": "CarePAK Plus",
        "carePakSku": 6653812751,
        "carePakSkuName": "CPPBINO_2894",
        "company": "BRISTO",
        "productGroup": "Medical",
        "productCode": "AL",
        "level2Code": "A9",
        "dataRecovery": "Y",
        "prefix": "MSPDA",
        "term": 0,
        "edit": "<a href=\"#\" onclick=\"showEditSkuModal(6653812751)\">EDIT</a>"
      },
      {
        "carePakType": "CarePAK Plus",
        "carePakSku": 2687980551,
        "carePakSkuName": "CPPBINO_2894",
        "company": "KIDGREASE",
        "productGroup": "Printer",
        "productCode": "BN",
        "level2Code": "C5",
        "dataRecovery": "Y",
        "prefix": "MSPDA",
        "term": 7,
        "edit": "<a href=\"#\" onclick=\"showEditSkuModal(2687980551)\">EDIT</a>"
      },
      {
        "carePakType": "CarePAK Plus",
        "carePakSku": 4349808382,
        "carePakSkuName": "CRRLINO_0504",
        "company": "CENTICE",
        "productGroup": "Boniculars",
        "productCode": "CM",
        "level2Code": "A2",
        "dataRecovery": "N",
        "prefix": "OTHER",
        "term": 14,
        "edit": "<a href=\"#\" onclick=\"showEditSkuModal(4349808382)\">EDIT</a>"
      },
      {
        "carePakType": "CarePAK Plus",
        "carePakSku": 8697305229,
        "carePakSkuName": "CPPBINO_2894",
        "company": "MANGLO",
        "productGroup": "Printer",
        "productCode": "AL",
        "level2Code": "C5",
        "dataRecovery": "Y",
        "prefix": "ESPDA",
        "term": 21,
        "edit": "<a href=\"#\" onclick=\"showEditSkuModal(8697305229)\">EDIT</a>"
      },
      {
        "carePakType": "CarePAK Plus",
        "carePakSku": 4683698099,
        "carePakSkuName": "CPPBINO_0504",
        "company": "INSURESYS",
        "productGroup": "Camera",
        "productCode": "CM",
        "level2Code": "A2",
        "dataRecovery": "N",
        "prefix": "ESPDA",
        "term": 0,
        "edit": "<a href=\"#\" onclick=\"showEditSkuModal(4683698099)\">EDIT</a>"
      },
      {
        "carePakType": "CarePAK Plus",
        "carePakSku": 5425422485,
        "carePakSkuName": "CPPBINO_0504",
        "company": "KOOGLE",
        "productGroup": "Printer",
        "productCode": "CM",
        "level2Code": "B3",
        "dataRecovery": "N",
        "prefix": "ESPDA",
        "term": 19,
        "edit": "<a href=\"#\" onclick=\"showEditSkuModal(5425422485)\">EDIT</a>"
      },
      {
        "carePakType": "CarePAK Plus",
        "carePakSku": 7603749875,
        "carePakSkuName": "CPPBINO_2894",
        "company": "INEAR",
        "productGroup": "Printer",
        "productCode": "TS",
        "level2Code": "B3",
        "dataRecovery": "N",
        "prefix": "ESPDAR",
        "term": 9,
        "edit": "<a href=\"#\" onclick=\"showEditSkuModal(7603749875)\">EDIT</a>"
      },
      {
        "carePakType": "CarePAK Plus",
        "carePakSku": 3850235919,
        "carePakSkuName": "CPPBINO_9836",
        "company": "TETRATREX",
        "productGroup": "Medical",
        "productCode": "BN",
        "level2Code": "C5",
        "dataRecovery": "N",
        "prefix": "MSPDA",
        "term": 9,
        "edit": "<a href=\"#\" onclick=\"showEditSkuModal(3850235919)\">EDIT</a>"
      },
      {
        "carePakType": "CarePAK Plus",
        "carePakSku": 4757902371,
        "carePakSkuName": "CPPBINO_29845",
        "company": "FURNITECH",
        "productGroup": "Boniculars",
        "productCode": "AL",
        "level2Code": "A2",
        "dataRecovery": "N",
        "prefix": "OTHER",
        "term": 21,
        "edit": "<a href=\"#\" onclick=\"showEditSkuModal(4757902371)\">EDIT</a>"
      },
      {
        "carePakType": "CarePAK Plus",
        "carePakSku": 2809122233,
        "carePakSkuName": "CPPBINO_9836",
        "company": "MUSANPOLY",
        "productGroup": "Boniculars",
        "productCode": "CM",
        "level2Code": "C5",
        "dataRecovery": "N",
        "prefix": "ESPDAR",
        "term": 6,
        "edit": "<a href=\"#\" onclick=\"showEditSkuModal(2809122233)\">EDIT</a>"
      },
      {
        "carePakType": "CarePAK Plus",
        "carePakSku": 1083672410,
        "carePakSkuName": "CRRLINO_0504",
        "company": "TRIPSCH",
        "productGroup": "Printer",
        "productCode": "BN",
        "level2Code": "B3",
        "dataRecovery": "N",
        "prefix": "ESPDAR",
        "term": 0,
        "edit": "<a href=\"#\" onclick=\"showEditSkuModal(1083672410)\">EDIT</a>"
      }
    ]
}